mimedb.py
mimedb-0.1.3.dist-info/WHEEL
mimedb-0.1.3.dist-info/METADATA
mimedb-0.1.3.dist-info/RECORD
