Metadata-Version: 2.3
Name: mimedb
Version: 0.1.3
Summary: Sqlite db to store any content with mime type.
Requires-Python: >=3.12
